datapath/__init__.py
datapath/path.py
tests/__init__.py
tests/conftest.py
tests/test_path.py
datapath-0.0.5.dist-info/LICENSE
datapath-0.0.5.dist-info/METADATA
datapath-0.0.5.dist-info/WHEEL
datapath-0.0.5.dist-info/top_level.txt
datapath-0.0.5.dist-info/RECORD
