Metadata-Version: 2.2
Name: datapath
Version: 0.0.5
Summary: Easily navigate nested data structures for building readable data pipelines.
Home-page: https://github.com/MasonFlint44/datapath
Author: Mason Flint
Author-email: masonflint44@gmail.com
Project-URL: Bug Tracker, https://github.com/MasonFlint44/datapath/issues
Classifier: Programming Language :: Python :: 3
Classifier: License :: OSI Approved :: MIT License
Classifier: Operating System :: OS Independent
Classifier: Development Status :: 3 - Alpha
Classifier: Intended Audience :: Developers
Requires-Python: >=3.10
License-File: LICENSE
